[
  {
    "word": "cold war",
    "tags": {
      "Domain": "history",
      "Generation": "Boomer",
      "AffectiveTone": "mysterious"
    }
  },
  {
    "word": "collective",
    "tags": {
      "Generation": "Gen Z",
      "PersonalityLens": "organizer",
      "Subculture": "art"
    }
  },
  {
    "word": "comfort",
    "tags": {
      "AffectiveTone": "typically humorous",
      "Domain": "emotion",
      "PersonalityLens": "dreamer",
      "Subculture": "food culture"
    }
  },
  {
    "word": "commedia dell arte",
    "tags": {
      "Culture": "Western",
      "Subculture": "art",
      "AffectiveTone": "typically humorous",
      "Domain": "history"
    }
  },
  {
    "word": "commons",
    "tags": {
      "Culture": "Hybrid / global culture",
      "PersonalityLens": "healer",
      "Setting": "village"
    }
  },
  {
    "word": "company",
    "tags": {
      "AffectiveTone": "absurd",
      "Setting": "factory"
    }
  },
  {
    "word": "connoisseur",
    "tags": {
      "Culture": "Western",
      "PersonalityLens": "analyst",
      "Subculture": "nightlife"
    }
  },
  {
    "word": "contemplation",
    "tags": {
      "AffectiveTone": "peaceful",
      "Domain": "philosophy",
      "PersonalityLens": "mystic",
      "Setting": "temple"
    }
  },
  {
    "word": "convivencia",
    "tags": {
      "PersonalityLens": "organizer",
      "IdentityExperience": "diaspora",
      "Subculture": "nightlife",
      "Setting": "jungle"
    }
  },
  {
    "word": "corroboree",
    "tags": {
      "Culture": "Global Indigenous",
      "Generation": "Gen Alpha",
      "Subculture": "nightlife"
    }
  },
  {
    "word": "cosmic",
    "tags": {
      "Domain": "emotion",
      "AffectiveTone": "chaotic",
      "Generation": "Timeless",
      "Setting": "outer space"
    }
  },
  {
    "word": "cosmonaut",
    "tags": {
      "AffectiveTone": "mysterious",
      "Domain": "spirituality",
      "Setting": "outer space"
    }
  },
  {
    "word": "cosplay",
    "tags": {
      "AffectiveTone": "typically humorous",
      "Culture": "Central Asian",
      "Setting": "city",
      "Subculture": "fandoms"
    }
  },
  {
    "word": "cottagecore",
    "tags": {
      "AffectiveTone": "nostalgic",
      "Generation": "Futuristic",
      "PersonalityLens": "dreamer",
      "Setting": "village"
    }
  },
  {
    "word": "council",
    "tags": {
      "Culture": "African",
      "Domain": "fiction",
      "PersonalityLens": "dreamer"
    }
  },
  {
    "word": "cowboy",
    "tags": {
      "AffectiveTone": "melancholic",
      "PersonalityLens": "dreamer",
      "Setting": "outer space",
      "Generation": "Millennial"
    }
  },
  {
    "word": "cozy game",
    "tags": {
      "AffectiveTone": "peaceful",
      "Domain": "fiction",
      "Setting": "market",
      "Subculture": "gaming"
    }
  },
  {
    "word": "crafting",
    "tags": {
      "AffectiveTone": "peaceful",
      "Domain": "pop culture",
      "PersonalityLens": "doer"
    }
  },
  {
    "word": "cramming",
    "tags": {
      "Domain": "education & learning",
      "Generation": "Boomer",
      "PersonalityLens": "doer"
    }
  },
  {
    "word": "cringe",
    "tags": {
      "Culture": "Hybrid / global culture",
      "Generation": "Millennial",
      "PersonalityLens": "rebel",
      "AffectiveTone": "typically humorous"
    }
  },
  {
    "word": "crip couture",
    "tags": {
      "AffectiveTone": "rebellious",
      "IdentityExperience": "disabled / chronically ill",
      "PersonalityLens": "thinker",
      "Subculture": "fashion"
    }
  },
  {
    "word": "crip lit",
    "tags": {
      "Culture": "South Asian",
      "Domain": "fiction",
      "IdentityExperience": "disabled / chronically ill",
      "Subculture": "sports & fitness"
    }
  },
  {
    "word": "crip time",
    "tags": {
      "AffectiveTone": "nostalgic",
      "Generation": "Gen Z",
      "IdentityExperience": "disabled / chronically ill",
      "PersonalityLens": "rebel"
    }
  },
  {
    "word": "cross-fit",
    "tags": {
      "Culture": "Diasporic",
      "Subculture": "sports & fitness"
    }
  },
  {
    "word": "crowdsourcing",
    "tags": {
      "Culture": "Hybrid / global culture",
      "Domain": "science",
      "Subculture": "digital/online culture"
    }
  },
  {
    "word": "cruising",
    "tags": {
      "AffectiveTone": "mysterious",
      "IdentityExperience": "LGBTQ+",
      "PersonalityLens": "explorer"
    }
  },
  {
    "word": "cryo-sleep",
    "tags": {
      "Setting": "outer space",
      "Subculture": "digital/online culture",
      "Culture": "Western",
      "IdentityExperience": "disabled / chronically ill"
    }
  },
  {
    "word": "cryptid",
    "tags": {
      "Domain": "pop culture",
      "IdentityExperience": "disabled / chronically ill",
      "Setting": "jungle"
    }
  },
  {
    "word": "crystal healing",
    "tags": {
      "Domain": "pop culture",
      "PersonalityLens": "healer"
    }
  },
  {
    "word": "cult classic",
    "tags": {
      "Domain": "pop culture",
      "Subculture": "fandoms",
      "AffectiveTone": "mysterious"
    }
  }
]